RoboCore_SMW_SX1262M0/RoboCore_SMW_SX1262M0.py
RoboCore_SMW_SX1262M0/__init__.py
robocore_smw_sx1262m0-1.0.0.dist-info/METADATA
robocore_smw_sx1262m0-1.0.0.dist-info/WHEEL
robocore_smw_sx1262m0-1.0.0.dist-info/licenses/License.txt
robocore_smw_sx1262m0-1.0.0.dist-info/RECORD
