Metadata-Version: 2.1
Name: RoboCore_SMW-SX1262M0
Version: 1.0.0
Summary: Library created to facilitate the use of the SMW-SX1262M0 LoRaWAN module
Project-URL: Homepage, https://github.com/RoboCore/RoboCore_SMW-SX1262M0_Python
Project-URL: Store, https://www.robocore.net/hat-raspberry-pi/lorawan-hat-para-raspberry-pi
Author-email: RoboCore <projetos@robocore.net>
License-File: License.txt
Classifier: License :: OSI Approved :: GNU Lesser General Public License v3 (LGPLv3)
Classifier: Operating System :: OS Independent
Classifier: Programming Language :: Python :: 3
Requires-Python: >=3.9.2
